neth/__init__.py
neth/camera_hacking.py
neth/hidden_network.py
neth/network_info.py
neth/wifi_cracker.py
neth/wifi_scanner.py
neth-0.3.dist-info/LICENSE
neth-0.3.dist-info/METADATA
neth-0.3.dist-info/WHEEL
neth-0.3.dist-info/top_level.txt
neth-0.3.dist-info/RECORD
